{
  "binList": [
    {
      "implMode": "high_performance",
      "int64Mode": false,
      "simplifiedKeyMode": 0,
      "simplifiedKey": [
        "ApplyCamePart3/d=0,p=1/0,2/27,2/0,2/0,2/0,2/0,2/27,2/0,2/0,2/0,2",
        "ApplyCamePart3/d=0,p=0/0,2/27,2/0,2/0,2/0,2/0,2/27,2/0,2/0,2/0,2"
      ],
      "optionalInputMode": "gen_placeholder",
      "optionalOutputMode": "gen_placeholder",
      "staticKey": "b4dc22cae1dae01067688fc363c161bb3b7862e56876d022caf27abcf2f1d76a,85fa868fa175ac6eab6b13031196614cb6871cd8229ed0b160ee73a934582ef9",
      "inputs": [
        {
          "name": "u",
          "index": 0,
          "dtype": "float32",
          "format": "ND",
          "paramType": "required",
          "shape": [
            -2
          ]
        },
        {
          "name": "m",
          "index": 1,
          "dtype": "bfloat16",
          "format": "ND",
          "paramType": "required",
          "shape": [
            -2
          ]
        },
        {
          "name": "eps",
          "index": 2,
          "dtype": "float32",
          "format": "ND",
          "paramType": "required",
          "shape": [
            -2
          ]
        },
        {
          "name": "beta1",
          "index": 3,
          "dtype": "float32",
          "format": "ND",
          "paramType": "required",
          "shape": [
            -2
          ]
        },
        {
          "name": "clip_threshold",
          "index": 4,
          "dtype": "float32",
          "format": "ND",
          "paramType": "required",
          "shape": [
            -2
          ]
        },
        {
          "name": "sum_square_u",
          "index": 5,
          "dtype": "float32",
          "format": "ND",
          "paramType": "required",
          "shape": [
            -2
          ]
        },
        {
          "name": "global_shape",
          "index": 6,
          "dtype": "int64",
          "format": "ND",
          "paramType": "optional",
          "shape": [
            -2
          ]
        }
      ],
      "outputs": [
        {
          "name": "m",
          "index": 0,
          "dtype": "bfloat16",
          "format": "ND",
          "paramType": "required",
          "shape": [
            -2
          ]
        },
        {
          "name": "sum_u_r",
          "index": 1,
          "dtype": "float32",
          "format": "ND",
          "paramType": "required",
          "shape": [
            -2
          ]
        },
        {
          "name": "sum_u_c",
          "index": 2,
          "dtype": "float32",
          "format": "ND",
          "paramType": "required",
          "shape": [
            -2
          ]
        },
        {
          "name": "sum_u_rc",
          "index": 3,
          "dtype": "float32",
          "format": "ND",
          "paramType": "required",
          "shape": [
            -2
          ]
        }
      ],
      "attrs": [
        {
          "name": "use_first_moment",
          "dtype": "bool",
          "value": false
        }
      ],
      "opMode": "dynamic",
      "deterministic": "false",
      "binInfo": {
        "jsonFilePath": "ascend910b/apply_came_part3/ApplyCamePart3_b81969c40c87acce26f390742e81a8ba_high_performance.json"
      }
    },
    {
      "implMode": "high_performance",
      "int64Mode": false,
      "simplifiedKeyMode": 0,
      "simplifiedKey": [
        "ApplyCamePart3/d=1,p=1/0,2/27,2/0,2/0,2/0,2/0,2/27,2/0,2/0,2/0,2",
        "ApplyCamePart3/d=1,p=0/0,2/27,2/0,2/0,2/0,2/0,2/27,2/0,2/0,2/0,2"
      ],
      "optionalInputMode": "gen_placeholder",
      "optionalOutputMode": "gen_placeholder",
      "staticKey": "b4dc22cae1dae01067688fc363c161bb3b7862e56876d022caf27abcf2f1d76a,85fa868fa175ac6eab6b13031196614cb6871cd8229ed0b160ee73a934582ef9",
      "inputs": [
        {
          "name": "u",
          "index": 0,
          "dtype": "float32",
          "format": "ND",
          "paramType": "required",
          "shape": [
            -2
          ]
        },
        {
          "name": "m",
          "index": 1,
          "dtype": "bfloat16",
          "format": "ND",
          "paramType": "required",
          "shape": [
            -2
          ]
        },
        {
          "name": "eps",
          "index": 2,
          "dtype": "float32",
          "format": "ND",
          "paramType": "required",
          "shape": [
            -2
          ]
        },
        {
          "name": "beta1",
          "index": 3,
          "dtype": "float32",
          "format": "ND",
          "paramType": "required",
          "shape": [
            -2
          ]
        },
        {
          "name": "clip_threshold",
          "index": 4,
          "dtype": "float32",
          "format": "ND",
          "paramType": "required",
          "shape": [
            -2
          ]
        },
        {
          "name": "sum_square_u",
          "index": 5,
          "dtype": "float32",
          "format": "ND",
          "paramType": "required",
          "shape": [
            -2
          ]
        },
        {
          "name": "global_shape",
          "index": 6,
          "dtype": "int64",
          "format": "ND",
          "paramType": "optional",
          "shape": [
            -2
          ]
        }
      ],
      "outputs": [
        {
          "name": "m",
          "index": 0,
          "dtype": "bfloat16",
          "format": "ND",
          "paramType": "required",
          "shape": [
            -2
          ]
        },
        {
          "name": "sum_u_r",
          "index": 1,
          "dtype": "float32",
          "format": "ND",
          "paramType": "required",
          "shape": [
            -2
          ]
        },
        {
          "name": "sum_u_c",
          "index": 2,
          "dtype": "float32",
          "format": "ND",
          "paramType": "required",
          "shape": [
            -2
          ]
        },
        {
          "name": "sum_u_rc",
          "index": 3,
          "dtype": "float32",
          "format": "ND",
          "paramType": "required",
          "shape": [
            -2
          ]
        }
      ],
      "attrs": [
        {
          "name": "use_first_moment",
          "dtype": "bool",
          "value": false
        }
      ],
      "opMode": "dynamic",
      "deterministic": "true",
      "binInfo": {
        "jsonFilePath": "ascend910b/apply_came_part3/ApplyCamePart3_b81969c40c87acce26f390742e81a8ba_high_performance_deterministic.json"
      }
    },
    {
      "implMode": "high_performance",
      "int64Mode": false,
      "simplifiedKeyMode": 0,
      "simplifiedKey": [
        "ApplyCamePart3/d=0,p=1/0,2/1,2/0,2/0,2/0,2/0,2/1,2/0,2/0,2/0,2",
        "ApplyCamePart3/d=0,p=0/0,2/1,2/0,2/0,2/0,2/0,2/1,2/0,2/0,2/0,2"
      ],
      "optionalInputMode": "gen_placeholder",
      "optionalOutputMode": "gen_placeholder",
      "staticKey": "2f6f1d346633c535e60f6cde340894d34a136e62e0daa62ce71c350a88779a2c,e7dc1b457935699521b1fafe554688fa129ea5a0fcb9b9a3d81575ca887df41e",
      "inputs": [
        {
          "name": "u",
          "index": 0,
          "dtype": "float32",
          "format": "ND",
          "paramType": "required",
          "shape": [
            -2
          ]
        },
        {
          "name": "m",
          "index": 1,
          "dtype": "float16",
          "format": "ND",
          "paramType": "required",
          "shape": [
            -2
          ]
        },
        {
          "name": "eps",
          "index": 2,
          "dtype": "float32",
          "format": "ND",
          "paramType": "required",
          "shape": [
            -2
          ]
        },
        {
          "name": "beta1",
          "index": 3,
          "dtype": "float32",
          "format": "ND",
          "paramType": "required",
          "shape": [
            -2
          ]
        },
        {
          "name": "clip_threshold",
          "index": 4,
          "dtype": "float32",
          "format": "ND",
          "paramType": "required",
          "shape": [
            -2
          ]
        },
        {
          "name": "sum_square_u",
          "index": 5,
          "dtype": "float32",
          "format": "ND",
          "paramType": "required",
          "shape": [
            -2
          ]
        },
        {
          "name": "global_shape",
          "index": 6,
          "dtype": "int64",
          "format": "ND",
          "paramType": "optional",
          "shape": [
            -2
          ]
        }
      ],
      "outputs": [
        {
          "name": "m",
          "index": 0,
          "dtype": "float16",
          "format": "ND",
          "paramType": "required",
          "shape": [
            -2
          ]
        },
        {
          "name": "sum_u_r",
          "index": 1,
          "dtype": "float32",
          "format": "ND",
          "paramType": "required",
          "shape": [
            -2
          ]
        },
        {
          "name": "sum_u_c",
          "index": 2,
          "dtype": "float32",
          "format": "ND",
          "paramType": "required",
          "shape": [
            -2
          ]
        },
        {
          "name": "sum_u_rc",
          "index": 3,
          "dtype": "float32",
          "format": "ND",
          "paramType": "required",
          "shape": [
            -2
          ]
        }
      ],
      "attrs": [
        {
          "name": "use_first_moment",
          "dtype": "bool",
          "value": false
        }
      ],
      "opMode": "dynamic",
      "deterministic": "false",
      "binInfo": {
        "jsonFilePath": "ascend910b/apply_came_part3/ApplyCamePart3_0ce3216e63292f4a186a79802125d72a_high_performance.json"
      }
    },
    {
      "implMode": "high_performance",
      "int64Mode": false,
      "simplifiedKeyMode": 0,
      "simplifiedKey": [
        "ApplyCamePart3/d=1,p=1/0,2/1,2/0,2/0,2/0,2/0,2/1,2/0,2/0,2/0,2",
        "ApplyCamePart3/d=1,p=0/0,2/1,2/0,2/0,2/0,2/0,2/1,2/0,2/0,2/0,2"
      ],
      "optionalInputMode": "gen_placeholder",
      "optionalOutputMode": "gen_placeholder",
      "staticKey": "2f6f1d346633c535e60f6cde340894d34a136e62e0daa62ce71c350a88779a2c,e7dc1b457935699521b1fafe554688fa129ea5a0fcb9b9a3d81575ca887df41e",
      "inputs": [
        {
          "name": "u",
          "index": 0,
          "dtype": "float32",
          "format": "ND",
          "paramType": "required",
          "shape": [
            -2
          ]
        },
        {
          "name": "m",
          "index": 1,
          "dtype": "float16",
          "format": "ND",
          "paramType": "required",
          "shape": [
            -2
          ]
        },
        {
          "name": "eps",
          "index": 2,
          "dtype": "float32",
          "format": "ND",
          "paramType": "required",
          "shape": [
            -2
          ]
        },
        {
          "name": "beta1",
          "index": 3,
          "dtype": "float32",
          "format": "ND",
          "paramType": "required",
          "shape": [
            -2
          ]
        },
        {
          "name": "clip_threshold",
          "index": 4,
          "dtype": "float32",
          "format": "ND",
          "paramType": "required",
          "shape": [
            -2
          ]
        },
        {
          "name": "sum_square_u",
          "index": 5,
          "dtype": "float32",
          "format": "ND",
          "paramType": "required",
          "shape": [
            -2
          ]
        },
        {
          "name": "global_shape",
          "index": 6,
          "dtype": "int64",
          "format": "ND",
          "paramType": "optional",
          "shape": [
            -2
          ]
        }
      ],
      "outputs": [
        {
          "name": "m",
          "index": 0,
          "dtype": "float16",
          "format": "ND",
          "paramType": "required",
          "shape": [
            -2
          ]
        },
        {
          "name": "sum_u_r",
          "index": 1,
          "dtype": "float32",
          "format": "ND",
          "paramType": "required",
          "shape": [
            -2
          ]
        },
        {
          "name": "sum_u_c",
          "index": 2,
          "dtype": "float32",
          "format": "ND",
          "paramType": "required",
          "shape": [
            -2
          ]
        },
        {
          "name": "sum_u_rc",
          "index": 3,
          "dtype": "float32",
          "format": "ND",
          "paramType": "required",
          "shape": [
            -2
          ]
        }
      ],
      "attrs": [
        {
          "name": "use_first_moment",
          "dtype": "bool",
          "value": false
        }
      ],
      "opMode": "dynamic",
      "deterministic": "true",
      "binInfo": {
        "jsonFilePath": "ascend910b/apply_came_part3/ApplyCamePart3_0ce3216e63292f4a186a79802125d72a_high_performance_deterministic.json"
      }
    },
    {
      "implMode": "high_performance",
      "int64Mode": false,
      "simplifiedKeyMode": 0,
      "simplifiedKey": [
        "ApplyCamePart3/d=0,p=1/0,2/0,2/0,2/0,2/0,2/0,2/0,2/0,2/0,2/0,2",
        "ApplyCamePart3/d=0,p=0/0,2/0,2/0,2/0,2/0,2/0,2/0,2/0,2/0,2/0,2"
      ],
      "optionalInputMode": "gen_placeholder",
      "optionalOutputMode": "gen_placeholder",
      "staticKey": "a58f9ad5695d2cc5fe31810b7331d677bd5c84043188fea12c5e8ea20d122f53,d8475876a6a93b2b86c195e2434d56d5a0565cd67436c69be5874ff471893ec7",
      "inputs": [
        {
          "name": "u",
          "index": 0,
          "dtype": "float32",
          "format": "ND",
          "paramType": "required",
          "shape": [
            -2
          ]
        },
        {
          "name": "m",
          "index": 1,
          "dtype": "float32",
          "format": "ND",
          "paramType": "required",
          "shape": [
            -2
          ]
        },
        {
          "name": "eps",
          "index": 2,
          "dtype": "float32",
          "format": "ND",
          "paramType": "required",
          "shape": [
            -2
          ]
        },
        {
          "name": "beta1",
          "index": 3,
          "dtype": "float32",
          "format": "ND",
          "paramType": "required",
          "shape": [
            -2
          ]
        },
        {
          "name": "clip_threshold",
          "index": 4,
          "dtype": "float32",
          "format": "ND",
          "paramType": "required",
          "shape": [
            -2
          ]
        },
        {
          "name": "sum_square_u",
          "index": 5,
          "dtype": "float32",
          "format": "ND",
          "paramType": "required",
          "shape": [
            -2
          ]
        },
        {
          "name": "global_shape",
          "index": 6,
          "dtype": "int64",
          "format": "ND",
          "paramType": "optional",
          "shape": [
            -2
          ]
        }
      ],
      "outputs": [
        {
          "name": "m",
          "index": 0,
          "dtype": "float32",
          "format": "ND",
          "paramType": "required",
          "shape": [
            -2
          ]
        },
        {
          "name": "sum_u_r",
          "index": 1,
          "dtype": "float32",
          "format": "ND",
          "paramType": "required",
          "shape": [
            -2
          ]
        },
        {
          "name": "sum_u_c",
          "index": 2,
          "dtype": "float32",
          "format": "ND",
          "paramType": "required",
          "shape": [
            -2
          ]
        },
        {
          "name": "sum_u_rc",
          "index": 3,
          "dtype": "float32",
          "format": "ND",
          "paramType": "required",
          "shape": [
            -2
          ]
        }
      ],
      "attrs": [
        {
          "name": "use_first_moment",
          "dtype": "bool",
          "value": false
        }
      ],
      "opMode": "dynamic",
      "deterministic": "false",
      "binInfo": {
        "jsonFilePath": "ascend910b/apply_came_part3/ApplyCamePart3_1e20748d435f18b1ca00c0d2e8d89fb4_high_performance.json"
      }
    },
    {
      "implMode": "high_performance",
      "int64Mode": false,
      "simplifiedKeyMode": 0,
      "simplifiedKey": [
        "ApplyCamePart3/d=1,p=1/0,2/0,2/0,2/0,2/0,2/0,2/0,2/0,2/0,2/0,2",
        "ApplyCamePart3/d=1,p=0/0,2/0,2/0,2/0,2/0,2/0,2/0,2/0,2/0,2/0,2"
      ],
      "optionalInputMode": "gen_placeholder",
      "optionalOutputMode": "gen_placeholder",
      "staticKey": "a58f9ad5695d2cc5fe31810b7331d677bd5c84043188fea12c5e8ea20d122f53,d8475876a6a93b2b86c195e2434d56d5a0565cd67436c69be5874ff471893ec7",
      "inputs": [
        {
          "name": "u",
          "index": 0,
          "dtype": "float32",
          "format": "ND",
          "paramType": "required",
          "shape": [
            -2
          ]
        },
        {
          "name": "m",
          "index": 1,
          "dtype": "float32",
          "format": "ND",
          "paramType": "required",
          "shape": [
            -2
          ]
        },
        {
          "name": "eps",
          "index": 2,
          "dtype": "float32",
          "format": "ND",
          "paramType": "required",
          "shape": [
            -2
          ]
        },
        {
          "name": "beta1",
          "index": 3,
          "dtype": "float32",
          "format": "ND",
          "paramType": "required",
          "shape": [
            -2
          ]
        },
        {
          "name": "clip_threshold",
          "index": 4,
          "dtype": "float32",
          "format": "ND",
          "paramType": "required",
          "shape": [
            -2
          ]
        },
        {
          "name": "sum_square_u",
          "index": 5,
          "dtype": "float32",
          "format": "ND",
          "paramType": "required",
          "shape": [
            -2
          ]
        },
        {
          "name": "global_shape",
          "index": 6,
          "dtype": "int64",
          "format": "ND",
          "paramType": "optional",
          "shape": [
            -2
          ]
        }
      ],
      "outputs": [
        {
          "name": "m",
          "index": 0,
          "dtype": "float32",
          "format": "ND",
          "paramType": "required",
          "shape": [
            -2
          ]
        },
        {
          "name": "sum_u_r",
          "index": 1,
          "dtype": "float32",
          "format": "ND",
          "paramType": "required",
          "shape": [
            -2
          ]
        },
        {
          "name": "sum_u_c",
          "index": 2,
          "dtype": "float32",
          "format": "ND",
          "paramType": "required",
          "shape": [
            -2
          ]
        },
        {
          "name": "sum_u_rc",
          "index": 3,
          "dtype": "float32",
          "format": "ND",
          "paramType": "required",
          "shape": [
            -2
          ]
        }
      ],
      "attrs": [
        {
          "name": "use_first_moment",
          "dtype": "bool",
          "value": false
        }
      ],
      "opMode": "dynamic",
      "deterministic": "true",
      "binInfo": {
        "jsonFilePath": "ascend910b/apply_came_part3/ApplyCamePart3_1e20748d435f18b1ca00c0d2e8d89fb4_high_performance_deterministic.json"
      }
    }
  ]
}