{
  "binList": [
    {
      "int64Mode": false,
      "staticKey": "dea8ec0344ea74757019e066eb4d21f72291983a3026d67bf2e2953fe7df98eb",
      "inputs": [
        {
          "name": "input_size",
          "index": 0,
          "dtype": "int32",
          "format": "NCDHW",
          "ori_format": "NCDHW",
          "shape": [
            5
          ],
          "ori_shape": [
            5
          ]
        },
        {
          "name": "x",
          "index": 1,
          "dtype": "float16",
          "format": "NDC1HWC0",
          "ori_format": "NCDHW",
          "shape": [
            -1,
            -1,
            -1,
            -1,
            -1,
            -1
          ],
          "ori_shape": [
            -1,
            -1,
            -1,
            -1,
            -1
          ],
          "range": [
            [
              1,
              -1
            ],
            [
              1,
              -1
            ],
            [
              1,
              -1
            ],
            [
              1,
              -1
            ],
            [
              1,
              -1
            ],
            [
              1,
              -1
            ]
          ]
        },
        {
          "name": "filter",
          "index": 2,
          "dtype": "float16",
          "format": "FRACTAL_Z_3D",
          "ori_format": "NCDHW",
          "shape": [
            -1,
            -1,
            -1,
            -1
          ],
          "ori_shape": [
            -1,
            -1,
            -1,
            -1,
            -1
          ],
          "range": [
            [
              1,
              -1
            ],
            [
              1,
              -1
            ],
            [
              1,
              -1
            ],
            [
              1,
              -1
            ]
          ]
        },
        null,
        null
      ],
      "outputs": [
        {
          "name": "y",
          "index": 0,
          "dtype": "float16",
          "format": "NDC1HWC0",
          "ori_format": "NCDHW",
          "shape": [
            -1,
            -1,
            -1,
            -1,
            -1,
            -1
          ],
          "ori_shape": [
            -1,
            -1,
            -1,
            -1,
            -1
          ],
          "range": [
            [
              1,
              -1
            ],
            [
              1,
              -1
            ],
            [
              1,
              -1
            ],
            [
              1,
              -1
            ],
            [
              1,
              -1
            ],
            [
              1,
              -1
            ]
          ]
        }
      ],
      "attrs": [
        {
          "name": "strides",
          "dtype": "list_int",
          "value": [
            -1,
            -1,
            -1,
            -1,
            -1
          ]
        },
        {
          "name": "pads",
          "dtype": "list_int",
          "value": [
            -1,
            -1,
            -1,
            -1,
            -1,
            -1
          ]
        },
        {
          "name": "dilations",
          "dtype": "list_int",
          "value": [
            -1,
            -1,
            -1,
            -1,
            -1
          ]
        },
        {
          "name": "groups",
          "dtype": "int",
          "value": -1
        },
        {
          "name": "data_format",
          "dtype": "string",
          "value": "NCDHW"
        },
        {
          "name": "output_padding",
          "dtype": "list_int",
          "value": [
            -1,
            -1,
            -1,
            -1,
            -1,
            -1
          ]
        },
        {
          "name": "offset_x",
          "dtype": "int",
          "value": 0
        }
      ],
      "opMode": "dynamic",
      "deterministic": "ignore",
      "binInfo": {
        "jsonFilePath": "ascend910b/conv3d_transpose/Conv3DTranspose_NDC1HWC0_NDC1HWC0_FP16_FP16_NDC1HWC0_high_performance.json"
      }
    },
    {
      "int64Mode": false,
      "staticKey": "68da26ed419cd483035e803bd938d975f735c137a6c3f58730fa51d94f1751c4",
      "inputs": [
        {
          "name": "input_size",
          "index": 0,
          "dtype": "int32",
          "format": "NCDHW",
          "ori_format": "NCDHW",
          "shape": [
            5
          ],
          "ori_shape": [
            5
          ]
        },
        {
          "name": "x",
          "index": 1,
          "dtype": "bfloat16",
          "format": "NDC1HWC0",
          "ori_format": "NCDHW",
          "shape": [
            -1,
            -1,
            -1,
            -1,
            -1,
            -1
          ],
          "ori_shape": [
            -1,
            -1,
            -1,
            -1,
            -1
          ],
          "range": [
            [
              1,
              -1
            ],
            [
              1,
              -1
            ],
            [
              1,
              -1
            ],
            [
              1,
              -1
            ],
            [
              1,
              -1
            ],
            [
              1,
              -1
            ]
          ]
        },
        {
          "name": "filter",
          "index": 2,
          "dtype": "bfloat16",
          "format": "FRACTAL_Z_3D",
          "ori_format": "NCDHW",
          "shape": [
            -1,
            -1,
            -1,
            -1
          ],
          "ori_shape": [
            -1,
            -1,
            -1,
            -1,
            -1
          ],
          "range": [
            [
              1,
              -1
            ],
            [
              1,
              -1
            ],
            [
              1,
              -1
            ],
            [
              1,
              -1
            ]
          ]
        },
        null,
        null
      ],
      "outputs": [
        {
          "name": "y",
          "index": 0,
          "dtype": "bfloat16",
          "format": "NDC1HWC0",
          "ori_format": "NCDHW",
          "shape": [
            -1,
            -1,
            -1,
            -1,
            -1,
            -1
          ],
          "ori_shape": [
            -1,
            -1,
            -1,
            -1,
            -1
          ],
          "range": [
            [
              1,
              -1
            ],
            [
              1,
              -1
            ],
            [
              1,
              -1
            ],
            [
              1,
              -1
            ],
            [
              1,
              -1
            ],
            [
              1,
              -1
            ]
          ]
        }
      ],
      "attrs": [
        {
          "name": "strides",
          "dtype": "list_int",
          "value": [
            -1,
            -1,
            -1,
            -1,
            -1
          ]
        },
        {
          "name": "pads",
          "dtype": "list_int",
          "value": [
            -1,
            -1,
            -1,
            -1,
            -1,
            -1
          ]
        },
        {
          "name": "dilations",
          "dtype": "list_int",
          "value": [
            -1,
            -1,
            -1,
            -1,
            -1
          ]
        },
        {
          "name": "groups",
          "dtype": "int",
          "value": -1
        },
        {
          "name": "data_format",
          "dtype": "string",
          "value": "NCDHW"
        },
        {
          "name": "output_padding",
          "dtype": "list_int",
          "value": [
            -1,
            -1,
            -1,
            -1,
            -1,
            -1
          ]
        },
        {
          "name": "offset_x",
          "dtype": "int",
          "value": 0
        }
      ],
      "opMode": "dynamic",
      "deterministic": "ignore",
      "binInfo": {
        "jsonFilePath": "ascend910b/conv3d_transpose/Conv3DTranspose_NDC1HWC0_NDC1HWC0_BF16_BF16_NDC1HWC0_high_performance.json"
      }
    }
  ]
}